odoo/addons/sale_order_line_delivery_state/README.rst
odoo/addons/sale_order_line_delivery_state/__init__.py
odoo/addons/sale_order_line_delivery_state/__manifest__.py
odoo/addons/sale_order_line_delivery_state/i18n/sale_order_line_delivery_state.pot
odoo/addons/sale_order_line_delivery_state/models/__init__.py
odoo/addons/sale_order_line_delivery_state/models/sale_order_line.py
odoo/addons/sale_order_line_delivery_state/readme/CONTRIBUTORS.rst
odoo/addons/sale_order_line_delivery_state/readme/DESCRIPTION.rst
odoo/addons/sale_order_line_delivery_state/static/description/icon.png
odoo/addons/sale_order_line_delivery_state/static/description/index.html
odoo/addons/sale_order_line_delivery_state/tests/__init__.py
odoo/addons/sale_order_line_delivery_state/tests/test_sale_line_delivery_state.py
odoo/addons/sale_order_line_delivery_state/views/sale_order_views.xml
odoo13_addon_sale_order_line_delivery_state-13.0.1.0.1.dev3.dist-info/METADATA
odoo13_addon_sale_order_line_delivery_state-13.0.1.0.1.dev3.dist-info/WHEEL
odoo13_addon_sale_order_line_delivery_state-13.0.1.0.1.dev3.dist-info/top_level.txt
odoo13_addon_sale_order_line_delivery_state-13.0.1.0.1.dev3.dist-info/RECORD
